{
    "code": 1,
    "message": "Success",
    "data": {
        "list": [
            {
                "docid": "14095880130233107274",
                "duration": 317,
                "msg": "抱歉，该视频需升级新版QQ音乐后再播放下载",
                "mvName_hilight": "晴天",
                "mv_id": 293791,
                "mv_name": "晴天",
                "mv_pic_url": "http://y.gtimg.cn/music/photo_new/T015R640x360M10300061J2t0b0PPW.jpg",
                "notplay": 0,
                "pay": 0,
                "play_count": 119374201,
                "publish_date": "2003-07-29",
                "singerMID": "0025NhlN2yWrP4",
                "singerName_hilight": "<em>周杰伦</em>",
                "singer_list": [
                    {
                        "id": 4558,
                        "mid": "0025NhlN2yWrP4",
                        "name": "周杰伦",
                        "pmid": "0025NhlN2yWrP4_10",
                        "title": "周杰伦",
                        "type": 0,
                        "uin": 0
                    }
                ],
                "singer_name": "周杰伦",
                "singerid": 4558,
                "singertype": 0,
                "type": 0,
                "uploader_nick": "",
                "uploader_uin": "",
                "v_id": "w0026q7f01a",
                "version": 0,
                "video_switch": 1927,
                "watchid": 293791,
                "watchtype": 0
            },
            {
                "docid": "15504498684272523232",
                "duration": 243,
                "msg": "抱歉，该视频需升级新版QQ音乐后再播放下载",
                "mvName_hilight": "青花瓷",
                "mv_id": 55327,
                "mv_name": "青花瓷",
                "mv_pic_url": "http://y.gtimg.cn/music/photo_new/T015R640x360M101004Rpn422DDgk1.jpg",
                "notplay": 0,
                "pay": 0,
                "play_count": 55352694,
                "publish_date": "2010-07-02",
                "singerMID": "0025NhlN2yWrP4",
                "singerName_hilight": "<em>周杰伦</em>",
                "singer_list": [
                    {
                        "id": 4558,
                        "mid": "0025NhlN2yWrP4",
                        "name": "周杰伦",
                        "pmid": "0025NhlN2yWrP4_10",
                        "title": "周杰伦",
                        "type": 0,
                        "uin": 0
                    }
                ],
                "singer_name": "周杰伦",
                "singerid": 4558,
                "singertype": 0,
                "type": 0,
                "uploader_nick": "",
                "uploader_uin": "",
                "v_id": "l00131om505",
                "version": 0,
                "video_switch": 1927,
                "watchid": 55327,
                "watchtype": 0
            },
            {
                "docid": "17357039210348298615",
                "duration": 265,
                "msg": "抱歉，该视频需升级新版QQ音乐后再播放下载",
                "mvName_hilight": "搁浅",
                "mv_id": 55221,
                "mv_name": "搁浅",
                "mv_pic_url": "http://y.gtimg.cn/music/photo_new/T015R640x360M103004K3l0u3GTjCp.jpg",
                "notplay": 0,
                "pay": 0,
                "play_count": 32489548,
                "publish_date": "2010-07-01",
                "singerMID": "0025NhlN2yWrP4",
                "singerName_hilight": "<em>周杰伦</em>",
                "singer_list": [
                    {
                        "id": 4558,
                        "mid": "0025NhlN2yWrP4",
                        "name": "周杰伦",
                        "pmid": "0025NhlN2yWrP4_10",
                        "title": "周杰伦",
                        "type": 0,
                        "uin": 0
                    }
                ],
                "singer_name": "周杰伦",
                "singerid": 4558,
                "singertype": 0,
                "type": 0,
                "uploader_nick": "",
                "uploader_uin": "",
                "v_id": "x00135ao69x",
                "version": 0,
                "video_switch": 1927,
                "watchid": 55221,
                "watchtype": 0
            },
            {
                "docid": "12413261304555418210",
                "duration": 247,
                "msg": "",
                "mvName_hilight": "蒲公英的约定 (2007世界巡回演唱会)",
                "mv_id": 55272,
                "mv_name": "蒲公英的约定 (2007世界巡回演唱会)",
                "mv_pic_url": "http://y.gtimg.cn/music/photo_new/T015R640x360M101003O1ORH4XWmQL.jpg",
                "notplay": 0,
                "pay": 0,
                "play_count": 1960146,
                "publish_date": "2008-01-30",
                "singerMID": "0025NhlN2yWrP4",
                "singerName_hilight": "<em>周杰伦</em>",
                "singer_list": [
                    {
                        "id": 4558,
                        "mid": "0025NhlN2yWrP4",
                        "name": "周杰伦",
                        "pmid": "0025NhlN2yWrP4_10",
                        "title": "周杰伦",
                        "type": 0,
                        "uin": 0
                    }
                ],
                "singer_name": "周杰伦",
                "singerid": 4558,
                "singertype": 0,
                "type": 0,
                "uploader_nick": "",
                "uploader_uin": "",
                "v_id": "y00133fa6sw",
                "version": 0,
                "video_switch": 1951,
                "watchid": 55272,
                "watchtype": 0
            },
            {
                "docid": "6256304611382619081",
                "duration": 215,
                "msg": "抱歉，该视频需升级新版QQ音乐后再播放下载",
                "mvName_hilight": "告白气球",
                "mv_id": 1053277,
                "mv_name": "告白气球",
                "mv_pic_url": "http://y.gtimg.cn/music/photo_new/T015R640x360M101000zvsVL4Bsi25.jpg",
                "notplay": 0,
                "pay": 0,
                "play_count": 80148355,
                "publish_date": "2016-10-28",
                "singerMID": "0025NhlN2yWrP4",
                "singerName_hilight": "<em>周杰伦</em>",
                "singer_list": [
                    {
                        "id": 4558,
                        "mid": "0025NhlN2yWrP4",
                        "name": "周杰伦",
                        "pmid": "0025NhlN2yWrP4_10",
                        "title": "周杰伦",
                        "type": 0,
                        "uin": 0
                    }
                ],
                "singer_name": "周杰伦",
                "singerid": 4558,
                "singertype": 0,
                "type": 0,
                "uploader_nick": "",
                "uploader_uin": "",
                "v_id": "u00222le4ox",
                "version": 0,
                "video_switch": 1927,
                "watchid": 1053277,
                "watchtype": 0
            },
            {
                "docid": "10693570050691514491",
                "duration": 299,
                "msg": "抱歉，该视频需升级新版QQ音乐后再播放下载",
                "mvName_hilight": "恒星不忘 Forever Forever",
                "mv_id": 2316062,
                "mv_name": "恒星不忘 Forever Forever",
                "mv_pic_url": "http://y.gtimg.cn/music/photo_new/T015R640x360M101002TCPwu3vWqmB.jpg",
                "notplay": 0,
                "pay": 0,
                "play_count": 430299,
                "publish_date": "2025-12-05",
                "singerMID": "0025NhlN2yWrP4",
                "singerName_hilight": "<em>周杰伦</em>/言承旭/吴建豪/周渝民/五月天 阿信",
                "singer_list": [
                    {
                        "id": 4558,
                        "mid": "0025NhlN2yWrP4",
                        "name": "周杰伦",
                        "pmid": "0025NhlN2yWrP4_10",
                        "title": "周杰伦",
                        "type": 0,
                        "uin": 0
                    },
                    {
                        "id": 4944,
                        "mid": "004VN9Ui1Omv94",
                        "name": "言承旭",
                        "pmid": "004VN9Ui1Omv94_3",
                        "title": "言承旭",
                        "type": 0,
                        "uin": 0
                    },
                    {
                        "id": 266,
                        "mid": "001Ue7bB0Bjbe8",
                        "name": "吴建豪",
                        "pmid": "001Ue7bB0Bjbe8_7",
                        "title": "吴建豪",
                        "type": 0,
                        "uin": 0
                    },
                    {
                        "id": 270,
                        "mid": "000ICvx62mc19U",
                        "name": "周渝民",
                        "pmid": "000ICvx62mc19U_3",
                        "title": "周渝民",
                        "type": 0,
                        "uin": 0
                    },
                    {
                        "id": 6617,
                        "mid": "0040EhGd2lkffO",
                        "name": "五月天 阿信",
                        "pmid": "0040EhGd2lkffO_2",
                        "title": "五月天 阿信",
                        "type": 0,
                        "uin": 0
                    }
                ],
                "singer_name": "周杰伦/言承旭/吴建豪/周渝民/五月天 阿信",
                "singerid": 4558,
                "singertype": 0,
                "type": 0,
                "uploader_nick": "",
                "uploader_uin": "",
                "v_id": "002TCPwu3vWqmB",
                "version": 0,
                "video_switch": 2023,
                "watchid": 2316062,
                "watchtype": 0
            },
            {
                "docid": "7394394899840251294",
                "duration": 264,
                "msg": "抱歉，该视频需升级新版QQ音乐后再播放下载",
                "mvName_hilight": "花海",
                "mv_id": 199394,
                "mv_name": "花海",
                "mv_pic_url": "http://y.gtimg.cn/music/photo_new/T015R640x360M102000o8suF4BZ0vX.jpg",
                "notplay": 0,
                "pay": 0,
                "play_count": 55705860,
                "publish_date": "2013-05-15",
                "singerMID": "0025NhlN2yWrP4",
                "singerName_hilight": "<em>周杰伦</em>",
                "singer_list": [
                    {
                        "id": 4558,
                        "mid": "0025NhlN2yWrP4",
                        "name": "周杰伦",
                        "pmid": "0025NhlN2yWrP4_10",
                        "title": "周杰伦",
                        "type": 0,
                        "uin": 0
                    }
                ],
                "singer_name": "周杰伦",
                "singerid": 4558,
                "singertype": 0,
                "type": 0,
                "uploader_nick": "",
                "uploader_uin": "",
                "v_id": "r00127x0yzd",
                "version": 0,
                "video_switch": 1927,
                "watchid": 199394,
                "watchtype": 0
            },
            {
                "docid": "7893875239730959784",
                "duration": 257,
                "msg": "抱歉，该视频需升级新版QQ音乐后再播放下载",
                "mvName_hilight": "说好的幸福呢",
                "mv_id": 202152,
                "mv_name": "说好的幸福呢",
                "mv_pic_url": "http://y.gtimg.cn/music/photo_new/T015R640x360M102004QhxPm1LpTDK.jpg",
                "notplay": 0,
                "pay": 0,
                "play_count": 26989618,
                "publish_date": "2013-06-17",
                "singerMID": "0025NhlN2yWrP4",
                "singerName_hilight": "<em>周杰伦</em>",
                "singer_list": [
                    {
                        "id": 4558,
                        "mid": "0025NhlN2yWrP4",
                        "name": "周杰伦",
                        "pmid": "0025NhlN2yWrP4_10",
                        "title": "周杰伦",
                        "type": 0,
                        "uin": 0
                    }
                ],
                "singer_name": "周杰伦",
                "singerid": 4558,
                "singertype": 0,
                "type": 0,
                "uploader_nick": "",
                "uploader_uin": "",
                "v_id": "r0012mpm057",
                "version": 0,
                "video_switch": 1927,
                "watchid": 202152,
                "watchtype": 0
            },
            {
                "docid": "10244983711222430465",
                "duration": 285,
                "msg": "抱歉，该视频需升级新版QQ音乐后再播放下载",
                "mvName_hilight": "爱你没差",
                "mv_id": 190915,
                "mv_name": "爱你没差",
                "mv_pic_url": "http://y.gtimg.cn/music/photo_new/T015R640x360M000002EoMXe2AwSvQ.jpg",
                "notplay": 0,
                "pay": 0,
                "play_count": 5509603,
                "publish_date": "2013-01-24",
                "singerMID": "0025NhlN2yWrP4",
                "singerName_hilight": "<em>周杰伦</em>",
                "singer_list": [
                    {
                        "id": 4558,
                        "mid": "0025NhlN2yWrP4",
                        "name": "周杰伦",
                        "pmid": "0025NhlN2yWrP4_10",
                        "title": "周杰伦",
                        "type": 0,
                        "uin": 0
                    }
                ],
                "singer_name": "周杰伦",
                "singerid": 4558,
                "singertype": 0,
                "type": 0,
                "uploader_nick": "",
                "uploader_uin": "",
                "v_id": "u0011kav4wg",
                "version": 0,
                "video_switch": 1927,
                "watchid": 190915,
                "watchtype": 0
            },
            {
                "docid": "12942397018584534256",
                "duration": 224,
                "msg": "抱歉，该视频需升级新版QQ音乐后再播放下载",
                "mvName_hilight": "稻香",
                "mv_id": 57370,
                "mv_name": "稻香",
                "mv_pic_url": "http://y.gtimg.cn/music/photo_new/T015R640x360M101003C7TmG43jmgE.jpg",
                "notplay": 0,
                "pay": 0,
                "play_count": 67502828,
                "publish_date": "2010-08-20",
                "singerMID": "0025NhlN2yWrP4",
                "singerName_hilight": "<em>周杰伦</em>",
                "singer_list": [
                    {
                        "id": 4558,
                        "mid": "0025NhlN2yWrP4",
                        "name": "周杰伦",
                        "pmid": "0025NhlN2yWrP4_10",
                        "title": "周杰伦",
                        "type": 0,
                        "uin": 0
                    }
                ],
                "singer_name": "周杰伦",
                "singerid": 4558,
                "singertype": 0,
                "type": 0,
                "uploader_nick": "",
                "uploader_uin": "",
                "v_id": "l0013kgn1be",
                "version": 0,
                "video_switch": 1927,
                "watchid": 57370,
                "watchtype": 0
            },
            {
                "docid": "15150720893823823253",
                "duration": 300,
                "msg": "抱歉，该视频需升级新版QQ音乐后再播放下载",
                "mvName_hilight": "发如雪",
                "mv_id": 36774,
                "mv_name": "发如雪",
                "mv_pic_url": "http://y.gtimg.cn/music/photo_new/T015R640x360M101003sTHbh2jJRYm.jpg",
                "notplay": 0,
                "pay": 0,
                "play_count": 13168122,
                "publish_date": "2009-04-30",
                "singerMID": "0025NhlN2yWrP4",
                "singerName_hilight": "<em>周杰伦</em>",
                "singer_list": [
                    {
                        "id": 4558,
                        "mid": "0025NhlN2yWrP4",
                        "name": "周杰伦",
                        "pmid": "0025NhlN2yWrP4_10",
                        "title": "周杰伦",
                        "type": 0,
                        "uin": 0
                    }
                ],
                "singer_name": "周杰伦",
                "singerid": 4558,
                "singertype": 0,
                "type": 0,
                "uploader_nick": "",
                "uploader_uin": "",
                "v_id": "g0022gfiw3p",
                "version": 0,
                "video_switch": 1927,
                "watchid": 36774,
                "watchtype": 0
            },
            {
                "docid": "16765610184559314283",
                "duration": 231,
                "msg": "抱歉，该视频需升级新版QQ音乐后再播放下载",
                "mvName_hilight": "夜曲",
                "mv_id": 125719,
                "mv_name": "夜曲",
                "mv_pic_url": "http://y.gtimg.cn/music/photo_new/T015R640x360M103000FBnWJ4KFLVl.jpg",
                "notplay": 0,
                "pay": 0,
                "play_count": 60152865,
                "publish_date": "2012-05-24",
                "singerMID": "0025NhlN2yWrP4",
                "singerName_hilight": "<em>周杰伦</em>",
                "singer_list": [
                    {
                        "id": 4558,
                        "mid": "0025NhlN2yWrP4",
                        "name": "周杰伦",
                        "pmid": "0025NhlN2yWrP4_10",
                        "title": "周杰伦",
                        "type": 0,
                        "uin": 0
                    }
                ],
                "singer_name": "周杰伦",
                "singerid": 4558,
                "singertype": 0,
                "type": 0,
                "uploader_nick": "",
                "uploader_uin": "",
                "v_id": "T0010Rcobut",
                "version": 0,
                "video_switch": 1927,
                "watchid": 125719,
                "watchtype": 0
            },
            {
                "docid": "9406396638457657850",
                "duration": 294,
                "msg": "抱歉，该视频需升级新版QQ音乐后再播放下载",
                "mvName_hilight": "手写的从前 (优酸乳为爱告白广告曲)",
                "mv_id": 304855,
                "mv_name": "手写的从前 (优酸乳为爱告白广告曲)",
                "mv_pic_url": "http://y.gtimg.cn/music/photo_new/T015R640x360M101000kCXLl27LsR0.jpg",
                "notplay": 0,
                "pay": 0,
                "play_count": 13833568,
                "publish_date": "2014-12-30",
                "singerMID": "0025NhlN2yWrP4",
                "singerName_hilight": "<em>周杰伦</em>",
                "singer_list": [
                    {
                        "id": 4558,
                        "mid": "0025NhlN2yWrP4",
                        "name": "周杰伦",
                        "pmid": "0025NhlN2yWrP4_10",
                        "title": "周杰伦",
                        "type": 0,
                        "uin": 0
                    }
                ],
                "singer_name": "周杰伦",
                "singerid": 4558,
                "singertype": 0,
                "type": 0,
                "uploader_nick": "",
                "uploader_uin": "",
                "v_id": "k0015ms0ov0",
                "version": 0,
                "video_switch": 1927,
                "watchid": 304855,
                "watchtype": 0
            },
            {
                "docid": "10131471231741818887",
                "duration": 246,
                "msg": "抱歉，该视频需升级新版QQ音乐后再播放下载",
                "mvName_hilight": "大笨钟",
                "mv_id": 179732,
                "mv_name": "大笨钟",
                "mv_pic_url": "http://y.gtimg.cn/music/photo_new/T015R640x360M101003ghMRa2UT1pX.jpg",
                "notplay": 0,
                "pay": 0,
                "play_count": 12851788,
                "publish_date": "2012-12-26",
                "singerMID": "0025NhlN2yWrP4",
                "singerName_hilight": "<em>周杰伦</em>",
                "singer_list": [
                    {
                        "id": 4558,
                        "mid": "0025NhlN2yWrP4",
                        "name": "周杰伦",
                        "pmid": "0025NhlN2yWrP4_10",
                        "title": "周杰伦",
                        "type": 0,
                        "uin": 0
                    }
                ],
                "singer_name": "周杰伦",
                "singerid": 4558,
                "singertype": 0,
                "type": 0,
                "uploader_nick": "",
                "uploader_uin": "",
                "v_id": "s0011s9kduo",
                "version": 0,
                "video_switch": 1927,
                "watchid": 179732,
                "watchtype": 0
            },
            {
                "docid": "897192485003028879",
                "duration": 302,
                "msg": "抱歉，该视频需升级新版QQ音乐后再播放下载",
                "mvName_hilight": "退后",
                "mv_id": 142062,
                "mv_name": "退后",
                "mv_pic_url": "http://y.gtimg.cn/music/photo_new/T015R640x360M101000fas3p24RIyD.jpg",
                "notplay": 0,
                "pay": 0,
                "play_count": 15010703,
                "publish_date": "2012-08-14",
                "singerMID": "0025NhlN2yWrP4",
                "singerName_hilight": "<em>周杰伦</em>",
                "singer_list": [
                    {
                        "id": 4558,
                        "mid": "0025NhlN2yWrP4",
                        "name": "周杰伦",
                        "pmid": "0025NhlN2yWrP4_10",
                        "title": "周杰伦",
                        "type": 0,
                        "uin": 0
                    }
                ],
                "singer_name": "周杰伦",
                "singerid": 4558,
                "singertype": 0,
                "type": 0,
                "uploader_nick": "",
                "uploader_uin": "",
                "v_id": "t0010RBkld2",
                "version": 0,
                "video_switch": 1927,
                "watchid": 142062,
                "watchtype": 0
            },
            {
                "docid": "12343568163487945828",
                "duration": 283,
                "msg": "抱歉，该视频需升级新版QQ音乐后再播放下载",
                "mvName_hilight": "说了再见 (《海洋天堂》电影主题曲)",
                "mv_id": 58340,
                "mv_name": "说了再见 (《海洋天堂》电影主题曲)",
                "mv_pic_url": "http://y.gtimg.cn/music/photo_new/T015R640x360M101004LDPBI04eKlr.jpg",
                "notplay": 0,
                "pay": 0,
                "play_count": 12867654,
                "publish_date": "2010-09-19",
                "singerMID": "0025NhlN2yWrP4",
                "singerName_hilight": "<em>周杰伦</em>",
                "singer_list": [
                    {
                        "id": 4558,
                        "mid": "0025NhlN2yWrP4",
                        "name": "周杰伦",
                        "pmid": "0025NhlN2yWrP4_10",
                        "title": "周杰伦",
                        "type": 0,
                        "uin": 0
                    }
                ],
                "singer_name": "周杰伦",
                "singerid": 4558,
                "singertype": 0,
                "type": 0,
                "uploader_nick": "",
                "uploader_uin": "",
                "v_id": "l0013t3fzcq",
                "version": 0,
                "video_switch": 1927,
                "watchid": 58340,
                "watchtype": 0
            },
            {
                "docid": "17166992752222697331",
                "duration": 303,
                "msg": "抱歉，该视频需升级新版QQ音乐后再播放下载",
                "mvName_hilight": "七里香",
                "mv_id": 55200,
                "mv_name": "七里香",
                "mv_pic_url": "http://y.gtimg.cn/music/photo_new/T015R640x360M101002nqnEb0stVkM.jpg",
                "notplay": 0,
                "pay": 0,
                "play_count": 60158193,
                "publish_date": "2010-07-01",
                "singerMID": "0025NhlN2yWrP4",
                "singerName_hilight": "<em>周杰伦</em>",
                "singer_list": [
                    {
                        "id": 4558,
                        "mid": "0025NhlN2yWrP4",
                        "name": "周杰伦",
                        "pmid": "0025NhlN2yWrP4_10",
                        "title": "周杰伦",
                        "type": 0,
                        "uin": 0
                    }
                ],
                "singer_name": "周杰伦",
                "singerid": 4558,
                "singertype": 0,
                "type": 0,
                "uploader_nick": "",
                "uploader_uin": "",
                "v_id": "k0013x8ao6z",
                "version": 0,
                "video_switch": 1927,
                "watchid": 55200,
                "watchtype": 0
            },
            {
                "docid": "7738987833967859615",
                "duration": 362,
                "msg": "抱歉，该视频需升级新版QQ音乐后再播放下载",
                "mvName_hilight": "以父之名",
                "mv_id": 55324,
                "mv_name": "以父之名",
                "mv_pic_url": "http://y.gtimg.cn/music/photo_new/T015R640x360M103002DrauO3SB6ZP.jpg",
                "notplay": 0,
                "pay": 0,
                "play_count": 19879268,
                "publish_date": "2010-07-02",
                "singerMID": "0025NhlN2yWrP4",
                "singerName_hilight": "<em>周杰伦</em>",
                "singer_list": [
                    {
                        "id": 4558,
                        "mid": "0025NhlN2yWrP4",
                        "name": "周杰伦",
                        "pmid": "0025NhlN2yWrP4_10",
                        "title": "周杰伦",
                        "type": 0,
                        "uin": 0
                    }
                ],
                "singer_name": "周杰伦",
                "singerid": 4558,
                "singertype": 0,
                "type": 0,
                "uploader_nick": "",
                "uploader_uin": "",
                "v_id": "r00138f4quj",
                "version": 0,
                "video_switch": 1927,
                "watchid": 55324,
                "watchtype": 0
            },
            {
                "docid": "17553294411828749376",
                "duration": 259,
                "msg": "抱歉，该视频需升级新版QQ音乐后再播放下载",
                "mvName_hilight": "明明就",
                "mv_id": 178381,
                "mv_name": "明明就",
                "mv_pic_url": "http://y.gtimg.cn/music/photo_new/T015R640x360M105000IgBec3gnBfv.jpg",
                "notplay": 0,
                "pay": 0,
                "play_count": 43160764,
                "publish_date": "2012-12-24",
                "singerMID": "0025NhlN2yWrP4",
                "singerName_hilight": "<em>周杰伦</em>",
                "singer_list": [
                    {
                        "id": 4558,
                        "mid": "0025NhlN2yWrP4",
                        "name": "周杰伦",
                        "pmid": "0025NhlN2yWrP4_10",
                        "title": "周杰伦",
                        "type": 0,
                        "uin": 0
                    }
                ],
                "singer_name": "周杰伦",
                "singerid": 4558,
                "singertype": 0,
                "type": 0,
                "uploader_nick": "",
                "uploader_uin": "",
                "v_id": "o00117sxevp",
                "version": 0,
                "video_switch": 1927,
                "watchid": 178381,
                "watchtype": 0
            },
            {
                "docid": "16736945877420227278",
                "duration": 278,
                "msg": "抱歉，该视频需升级新版QQ音乐后再播放下载",
                "mvName_hilight": "你听得到",
                "mv_id": 55528,
                "mv_name": "你听得到",
                "mv_pic_url": "http://y.gtimg.cn/music/photo_new/T015R640x360M102002cISBi2PoxWW.jpg",
                "notplay": 0,
                "pay": 0,
                "play_count": 5893172,
                "publish_date": "2010-07-06",
                "singerMID": "0025NhlN2yWrP4",
                "singerName_hilight": "<em>周杰伦</em>",
                "singer_list": [
                    {
                        "id": 4558,
                        "mid": "0025NhlN2yWrP4",
                        "name": "周杰伦",
                        "pmid": "0025NhlN2yWrP4_10",
                        "title": "周杰伦",
                        "type": 0,
                        "uin": 0
                    }
                ],
                "singer_name": "周杰伦",
                "singerid": 4558,
                "singertype": 0,
                "type": 0,
                "uploader_nick": "",
                "uploader_uin": "",
                "v_id": "s0013shybox",
                "version": 0,
                "video_switch": 1927,
                "watchid": 55528,
                "watchtype": 0
            }
        ],
        "page": 1,
        "size": 20,
        "total": 597,
        "key": "周杰伦"
    }
}